<recyclerItem>
  <pageItems>
    <pageItem name="" activeBegin="01/01/0001 00:00:00" activeEnd="01/01/0001 00:00:00" alwaysBuild="False" areaName="Standard" isActive="True" objectID="_07" rssFlag="False" styleName="sidebaricons" editorType="None" orderPosition="0" itemTemplateName="standard" wasCopiedFromArticleObjectID="_06">
      <excerpt>Icon 1</excerpt>
      <value name="icon1">fa-home</value>
      <value name="text1">Startseite</value>
      <value name="icon2">fa-phone</value>
      <value name="text2">Kontakt</value>
      <value name="icon3">fa-phone</value>
      <value name="text3">Telefon</value>
      <value name="alignment">right</value>
      <value name="alignmentTop">50%</value>
      <value name="iconWidth">45</value>
      <value name="iconHeight">45</value>
      <value name="borderRadius">3</value>
      <value name="borderWidth">1</value>
      <value name="iconMargin">1</value>
      <value name="iconFontSize">1em</value>
      <value name="showText">1</value>
      <value name="textWidth">80</value>
      <value name="textFontSize">0.8em</value>
      <value name="iconColor">#FFFFFF</value>
      <value name="backgroundColor">#0082D7</value>
      <value name="borderColor">#0082D7</value>
      <value name="shadowColor">rgba(0, 0, 0, 0.1)</value>
      <value name="iconColorHover">#FFFFFF</value>
      <value name="backgroundColorHover">#0076C4</value>
      <value name="borderColorHover">#0076C4</value>
      <value name="shadowColorHover">rgba(0, 0, 0, 0.2)</value>
      <value name="mobileBreakpoint">479</value>
      <value name="displayMobile">small</value>
      <value name="iconUrl1">oid://page/de$Ueber_uns</value>
      <value name="iconUrl1_target" />
      <value name="iconUrl1_nofollow">False</value>
      <value name="iconUrl2">oid://page/de$Kontakt</value>
      <value name="iconUrl2_target" />
      <value name="iconUrl2_nofollow">False</value>
      <value name="iconUrl3" />
      <value name="iconUrl3_target" />
      <value name="iconUrl3_nofollow">False</value>
      <value name="icon4" />
      <value name="iconUrl4" />
      <value name="iconUrl4_target" />
      <value name="iconUrl4_nofollow">False</value>
      <value name="text4" />
      <value name="icon5" />
      <value name="iconUrl5" />
      <value name="iconUrl5_target" />
      <value name="iconUrl5_nofollow">False</value>
      <value name="text5" />
      <value name="alignmentBottom" />
      <dynamicSettings>
        <value name="name-align" />
        <value name="name-color" />
        <value name="name-level">h2</value>
      </dynamicSettings>
    </pageItem>
  </pageItems>
</recyclerItem>